__init__.py
alignem.py
src/__init__.py
src/config.py
src/core/__init__.py
src/core/files.py
src/core/recipemaker.py
src/core/thumbnailer.py
src/core/validate.py
src/jobs/__init__.py
src/jobs/job_apply_affine.py
src/jobs/job_collate_spots.py
src/lib/_makefile.TACC
src/lib/_swim.c
src/lib/bin_darwin/iavg
src/lib/bin_darwin/iscale
src/lib/bin_darwin/iscale2
src/lib/bin_darwin/mir
src/lib/bin_darwin/remod
src/lib/bin_darwin/swim
src/lib/bin_tacc/iavg
src/lib/bin_tacc/iscale
src/lib/bin_tacc/iscale2
src/lib/bin_tacc/mir
src/lib/bin_tacc/remod
src/lib/bin_tacc/swim
src/lib/debug.h
src/lib/gifload.c
src/lib/iavg.c
src/lib/iscale.c
src/lib/iscale2.c
src/lib/makefile
src/lib/makefile.TACC
src/lib/makefile.darwin
src/lib/makefile.linux
src/lib/makefile.windows
src/lib/makefile_debug
src/lib/makefile_mod.TACC
src/lib/mir.c
src/lib/remod.c
src/lib/remod_old.c
src/lib/sha1sum.txt
src/lib/swim.c
src/lib/swimio.h
src/lib/sxox.c
src/lib/test_libs.c
src/models/__init__.py
src/models/cache.py
src/models/data.py
src/models/jsontree.py
src/models/preferences.py
src/resources/__init__.py
src/resources/cursors/match-point.png
src/resources/html/KeyboardCommands.html
src/resources/html/KeyboardCommands1.html
src/resources/html/faq.html
src/resources/html/features.html
src/resources/html/getting-started.html
src/resources/html/glossary.html
src/resources/html/ls6.html
src/resources/html/null.css
src/resources/html/null.html
src/resources/html/remod.html
src/resources/html/swiftir_components.html
src/resources/html/zarr-drawing.html
src/resources/html/zarr-nature-2021.html
src/resources/icons/3dem-icon.png
src/resources/icons/checkmark.png
src/resources/icons/close-tab-dark.png
src/resources/icons/close-tab-light.png
src/resources/icons/down-right.png
src/resources/icons/em-guy.png
src/resources/icons/key1.png
src/resources/icons/key2.png
src/resources/icons/key3.png
src/resources/icons/notepad.png
src/resources/icons/python.png
src/resources/icons/tacc-logo.png
alignem-0.6.0.dist-info/LICENSE.txt
alignem-0.6.0.dist-info/METADATA
alignem-0.6.0.dist-info/WHEEL
alignem-0.6.0.dist-info/entry_points.txt
alignem-0.6.0.dist-info/RECORD
