Metadata-Version: 2.1
Name: alignem
Version: 0.6.0
Summary: AlignEM is a GUI for aligning or 'registering' electron microscopy images using SWiFT-IR
License: Mozilla Public License Version 2.0
Author: Joel Yancey
Author-email: j.y@ucla.edu
Requires-Python: >=3.9,<4.0
Classifier: License :: Other/Proprietary License
Classifier: Programming Language :: Python :: 3
Classifier: Programming Language :: Python :: 3.9
Classifier: Programming Language :: Python :: 3.10
Classifier: Programming Language :: Python :: 3.11
Classifier: Programming Language :: Python :: 3.12
Requires-Dist: Pillow (>=9.5.0,<10.0.0)
Requires-Dist: PyQt5 (>=5.15.9,<6.0.0)
Requires-Dist: PyQtWebEngine (>=5.15.6,<6.0.0)
Requires-Dist: QtAwesome (>=1.2.3,<2.0.0)
Requires-Dist: QtPy (>=2.3.1,<3.0.0)
Requires-Dist: imagecodecs (>=2023.3.16,<2024.0.0)
Requires-Dist: imageio (>=2.28.0,<3.0.0)
Requires-Dist: neuroglancer (>=2.36,<3.0)
Requires-Dist: numpy (>=1.24.3,<2.0.0)
Requires-Dist: psutil (>=5.9.5,<6.0.0)
Requires-Dist: pylibtiff (>=0.5.1,<0.6.0)
Requires-Dist: pyqtgraph (>=0.13.3,<0.14.0)
Requires-Dist: qtconsole (>=5.4.1,<6.0.0)
Requires-Dist: tensorstore (>=0.1.36,<0.2.0)
Requires-Dist: tifffile (>=2023.4.12,<2024.0.0)
Requires-Dist: zarr (>=2.14.2,<3.0.0)
